vnhtr/__init__.py
vnhtr/source/__init__.py
vnhtr/source/app.py
vnhtr/source/augment.py
vnhtr/source/gen_images.py
vnhtr/source/gen_sentence.py
vnhtr/source/train_test_split.py
vnhtr/source/VGGTransformer/FCN_trainer.py
vnhtr/source/VGGTransformer/__init__.py
vnhtr/source/VGGTransformer/adapt_trainer.py
vnhtr/source/VGGTransformer/config.py
vnhtr/source/VGGTransformer/dataset.py
vnhtr/source/VGGTransformer/eval.py
vnhtr/source/VGGTransformer/finetune.py
vnhtr/source/VGGTransformer/gc_trainer.py
vnhtr/source/VGGTransformer/inference_time.py
vnhtr/source/VGGTransformer/jit.py
vnhtr/source/VGGTransformer/models.py
vnhtr/source/VGGTransformer/small_config.py
vnhtr/source/VGGTransformer/submodules.py
vnhtr/source/VGGTransformer/train.py
vnhtr/source/VGGTransformer/utils.py
vnhtr/source/VisionEncoderDecoder/__init__.py
vnhtr/source/VisionEncoderDecoder/adapter_trainer.py
vnhtr/source/VisionEncoderDecoder/config.py
vnhtr/source/VisionEncoderDecoder/dataset.py
vnhtr/source/VisionEncoderDecoder/eval.py
vnhtr/source/VisionEncoderDecoder/finetune.py
vnhtr/source/VisionEncoderDecoder/inference_time.py
vnhtr/source/VisionEncoderDecoder/jit.py
vnhtr/source/VisionEncoderDecoder/model.py
vnhtr/source/VisionEncoderDecoder/train.py
vnhtr/source/VisionEncoderDecoder/utils.py
vnhtr/vnhtr_script/__init__.py
vnhtr/vnhtr_script/tools.py
vnhtr-0.1.8.dist-info/LICENSE
vnhtr-0.1.8.dist-info/METADATA
vnhtr-0.1.8.dist-info/WHEEL
vnhtr-0.1.8.dist-info/top_level.txt
vnhtr-0.1.8.dist-info/RECORD
