Metadata-Version: 2.1
Name: vnhtr
Version: 0.1.8
Summary: Encoder-Decoder base for Vietnamese handwriting recognition
Home-page: https://github.com/nguyenhoanganh2002/vnhtr
Author: nguyenhoanganh2002
Author-email: anh.nh204511@gmail.com
Keywords: ocr,vnocr,htr,vnhtr
Classifier: Programming Language :: Python :: 3
Classifier: License :: OSI Approved :: MIT License
Classifier: Operating System :: OS Independent
Requires-Python: >=3.6
License-File: LICENSE
Requires-Dist: pillow
Requires-Dist: transformers (==4.35.0)
Requires-Dist: sentencepiece (==0.1.99)
